{
	"nodes": [
	{"id":"0", "label":"切る\n豚こま", "posx":20, "posy":10, "description":"豚こまを切る" },
	{"id":"1", "label":"切る\nじゃがいも\n大きめ", "posx":20, "posy":190, "description":"じゃがいもを大きめに切る" },
	{"id":"2", "label":"切る\n玉ねぎ", "posx":20, "posy":370, "description":"玉ねぎを切る" },
	{"id":"3", "label":"切る\nにんじん", "posx":20, "posy":550, "description":"にんじんを切る" },
	{"id":"4", "label":"入れる\nオリーブ\n大さじ2\n鍋", "posx":180, "posy":280, "description":"鍋にオリーブを大さじ2入れる" },
	{"id":"5", "label":"炒める\n肉\n鍋", "posx":340, "posy":280, "description":"鍋で肉を炒める" },
	{"id":"6", "label":"入れる\nじゃがいも\nたまねぎ\nにんじん\n火が通ったら", "posx":500, "posy":280, "description":"火が通ったらじゃがいも，たまねぎ，にんじんを入れる" },
	{"id":"7", "label":"炒める\n肉\nじゃがいも\n玉ねぎ\nにんじん", "posx":660, "posy":280, "description":"肉，じゃがいも，たまねぎ，にんじんを炒める" },
	{"id":"8", "label":"加える\n水(ヒタヒタ)\nみりん\n砂糖\n白だし", "posx":820, "posy":280, "description":"水，みりん，砂糖，白だしを加える", "failure":"しゃばしゃばになるから水の量を注意しよう" },
	{"id":"9", "label":"煮る", "posx":980, "posy":280, "description":"煮る" },
	{"id":"10", "label":"取り除く\nアク", "posx":1140, "posy":280, "description":"アクを取り除く"},
	{"id":"11", "label":"煮る\n中火\n15分", "posx":1300, "posy":280, "description":"中火で15分煮る"},
	{"id":"101", "label":"初級者用", "posx":740, "posy":550},	
	{"id":"201", "label":"しゃばしゃばに\nなるから\n水の量注意", "posx":900, "posy":550}
],
 "links": [
	{ "source" : 0, "target" : 4, "id":"0" },
	{ "source" : 1, "target" : 4, "id":"1" },
	{ "source" : 2, "target" : 4, "id":"2" },
	{ "source" : 3, "target" : 4, "id":"3" },
	{ "source" : 4, "target" : 5, "id":"4" },
	{ "source" : 5, "target" : 6, "id":"5" },
	{ "source" : 6, "target" : 7, "id":"6" },
	{ "source" : 7, "target" : 8, "id":"7" },
	{ "source" : 8, "target" : 9, "id":"8" },
	{ "source" : 9, "target" : 10, "id":"9" },
	{ "source" : 10, "target" : 11, "id":"10" },
	{ "source" : 11, "target" : 11, "id":"11" },
	{ "source" : 12, "target" : 7, "id":"101" },
	{ "source" : 13, "target" : 8, "id":"201" }
]
}


